openvas_edxml/__init__.py
openvas_edxml/brick.py
openvas_edxml/cli.py
openvas_edxml/logger.py
openvas_edxml/synthesize.py
openvas_edxml/version.py
openvas_edxml/transcoders/__init__.py
openvas_edxml/transcoders/error.py
openvas_edxml/transcoders/host.py
openvas_edxml/transcoders/report.py
openvas_edxml/transcoders/result.py
openvas_edxml-3.0.0.dist-info/LICENSE.rst
openvas_edxml-3.0.0.dist-info/METADATA
openvas_edxml-3.0.0.dist-info/WHEEL
openvas_edxml-3.0.0.dist-info/entry_points.txt
openvas_edxml-3.0.0.dist-info/top_level.txt
openvas_edxml-3.0.0.dist-info/RECORD
