Metadata-Version: 2.1
Name: openvas-edxml
Version: 3.0.0
Summary: An OpenVAS XML to EDXML transcoder
Home-page: https://github.com/dtakken/edxml-openvas
Author: Dik Takken
Author-email: d.h.j.takken@freedom.nl
License: MIT
Keywords: edxml openvas
Classifier: Development Status :: 5 - Production/Stable
Classifier: Intended Audience :: Developers
Classifier: Topic :: Security
Classifier: Topic :: Software Development :: Libraries :: Python Modules
Classifier: Topic :: Scientific/Engineering :: Artificial Intelligence
Classifier: License :: OSI Approved :: MIT License
Classifier: Programming Language :: Python :: 3
License-File: LICENSE.rst
Requires-Dist: edxml (~=3.0)
Requires-Dist: edxml-bricks-generic (~=3.0)
Requires-Dist: edxml-bricks-geography (~=3.0)
Requires-Dist: edxml-bricks-computing (~=3.0)
Requires-Dist: edxml-bricks-computing-networking (~=3.0)
Requires-Dist: edxml-bricks-computing-security (~=3.0)
Requires-Dist: cryptography
Requires-Dist: edxml-bricks-computing-forensics (~=3.0)
Requires-Dist: IPy
Requires-Dist: python-dateutil
